beancount_mbank/__init__.py
beancount_mbank/mbank.py
beancount_mbank-0.1.0.dist-info/AUTHORS.rst
beancount_mbank-0.1.0.dist-info/LICENSE
beancount_mbank-0.1.0.dist-info/METADATA
beancount_mbank-0.1.0.dist-info/WHEEL
beancount_mbank-0.1.0.dist-info/entry_points.txt
beancount_mbank-0.1.0.dist-info/top_level.txt
beancount_mbank-0.1.0.dist-info/RECORD
