Metadata-Version: 2.1
Name: beancount-mbank
Version: 0.1.0
Summary: Beancount Importer for mBank (PL) CSV exports
Home-page: https://github.com/lstrzepek/beancount-mbank
Author: Łukasz Strzępek
Author-email: lstrzepek@gmail.com
License: MIT
Project-URL: Documentation, https://beancount-mbank.readthedocs.io/
Project-URL: Changelog, https://beancount-mbank.readthedocs.io/en/latest/changelog.html
Project-URL: Issue Tracker, https://github.com/lstrzepek/beancount-mbank/issues
Keywords: banking,beancount,cli-accounting,finance
Classifier: Development Status :: 5 - Production/Stable
Classifier: Intended Audience :: Developers
Classifier: License :: OSI Approved :: MIT License
Classifier: Operating System :: Unix
Classifier: Operating System :: POSIX
Classifier: Operating System :: Microsoft :: Windows
Classifier: Programming Language :: Python
Classifier: Programming Language :: Python :: 3
Classifier: Programming Language :: Python :: 3 :: Only
Classifier: Programming Language :: Python :: 3.7
Classifier: Programming Language :: Python :: 3.8
Classifier: Programming Language :: Python :: 3.9
Classifier: Programming Language :: Python :: 3.10
Classifier: Programming Language :: Python :: 3.11
Classifier: Programming Language :: Python :: Implementation :: CPython
Classifier: Programming Language :: Python :: Implementation :: PyPy
Classifier: Topic :: Office/Business :: Financial :: Accounting
Requires-Python: >=3.7
License-File: LICENSE
License-File: AUTHORS.rst
Requires-Dist: beancount (>=2.3.5)
